pyRustScraperApi/__init__.py
pyRustScraperApi/base_client.py
pyRustScraperApi/client.py
pyRustScraperApi/models.py
pyrustscraperapi-1.0.5.dist-info/METADATA
pyrustscraperapi-1.0.5.dist-info/WHEEL
pyrustscraperapi-1.0.5.dist-info/licenses/LICENSE
pyrustscraperapi-1.0.5.dist-info/RECORD
