Metadata-Version: 2.4
Name: pyRustScraperApi
Version: 1.0.5
Summary: Python клиент для взаимодействия с RustScraperApi
Project-URL: Homepage, https://rustscraper.ru
Project-URL: Documentation, https://rustscraper.ru/swagger-ui/
Project-URL: Repository, https://github.com/Nikita55612/pyRustScraperApi
Author-email: Nikita5612 <groz.yt56@gmail.com>
License-Expression: MIT
License-File: LICENSE
Keywords: api,ozon,маркетплейс,озон,парсер,парсинг
Classifier: Operating System :: OS Independent
Classifier: Programming Language :: Python :: 3
Requires-Python: >=3.9
Requires-Dist: httpx==0.28.1
Requires-Dist: websockets==14.1
Provides-Extra: dev
Requires-Dist: black>=23.0; extra == 'dev'
Requires-Dist: isort>=5.0; extra == 'dev'
Requires-Dist: mypy>=1.0; extra == 'dev'
Requires-Dist: pytest>=7.0; extra == 'dev'
